libname/__init__.py
libname/hello.py
testhelloAlberPrueba-0.0.2.dist-info/METADATA
testhelloAlberPrueba-0.0.2.dist-info/WHEEL
testhelloAlberPrueba-0.0.2.dist-info/top_level.txt
testhelloAlberPrueba-0.0.2.dist-info/RECORD
