Metadata-Version: 2.1
Name: testhelloAlberPrueba
Version: 0.0.2
Summary: test hello
Home-page: UNKNOWN
Author: Alberto
Author-email: prueba@prueba.com
License: UNKNOWN
Keywords: python,AI
Platform: UNKNOWN
Classifier: Development Status :: 1 - Planning
Classifier: Intended Audience :: Developers
Classifier: Programming Language :: Python :: 3
Classifier: Operating System :: Unix
Classifier: Operating System :: MacOS :: MacOS X
Classifier: Operating System :: Microsoft :: Windows
Requires-Dist: scanpy
Requires-Dist: pandas
Requires-Dist: numpy
